Metadata-Version: 1.0
Name: jpud-distributions
Version: 1.0
Summary: Binomial and Gaussian distributions
Home-page: UNKNOWN
Author: Joao Paulo Ramos
Author-email: UNKNOWN
License: UNKNOWN
Platform: UNKNOWN
